clingy.py
clingy-1.0.0.dist-info/DESCRIPTION.rst
clingy-1.0.0.dist-info/METADATA
clingy-1.0.0.dist-info/RECORD
clingy-1.0.0.dist-info/WHEEL
clingy-1.0.0.dist-info/entry_points.txt
clingy-1.0.0.dist-info/metadata.json
clingy-1.0.0.dist-info/top_level.txt
