Metadata-Version: 2.0
Name: clingy
Version: 1.0.0
Summary: A tool to save attachments from plain text emails
Home-page: https://github.com/mtkennerly/clingy
Author: Matthew T. Kennerly (mtkennerly)
Author-email: mtkennerly@gmail.com
License: MIT
Keywords: email attachment
Platform: UNKNOWN
Classifier: Development Status :: 5 - Production/Stable
Classifier: Intended Audience :: End Users/Desktop
Classifier: License :: OSI Approved :: MIT License
Classifier: Natural Language :: English
Classifier: Programming Language :: Python
Classifier: Programming Language :: Python :: 2.7
Classifier: Programming Language :: Python :: 3
Classifier: Topic :: Communications :: Email
Classifier: Topic :: Utilities
Provides-Extra: test
Requires-Dist: mock; extra == 'test'
Requires-Dist: pytest; extra == 'test'
